aiorest_client.py
aiorest_client-0.2.2.dist-info/AUTHORS.rst
aiorest_client-0.2.2.dist-info/LICENSE
aiorest_client-0.2.2.dist-info/METADATA
aiorest_client-0.2.2.dist-info/WHEEL
aiorest_client-0.2.2.dist-info/top_level.txt
aiorest_client-0.2.2.dist-info/RECORD
