Metadata-Version: 2.1
Name: aiorest-client
Version: 0.2.2
Summary: A helper to call REST API from aiohttp
Home-page: https://github.com/klen/aiorest_client
Author: Kirill Klenov
Author-email: horneds@gmail.com
License: MIT license
Keywords: aiorest_client aiohttp rest api async
Platform: UNKNOWN
Classifier: Development Status :: 2 - Pre-Alpha
Classifier: Intended Audience :: Developers
Classifier: License :: OSI Approved :: MIT License
Classifier: Natural Language :: English
Classifier: Programming Language :: Python :: 3
Classifier: Programming Language :: Python :: 3.5
Classifier: Programming Language :: Python :: 3.6
Classifier: Programming Language :: Python :: 3.7
Requires-Dist: aiohttp (>=3.0.0)
